{
    "contact": {
        "complaint": "หน่วยงานรับเรื่องร้องเรียน",
        "complaint_tel": "tel:023534700",
        "complaint_info": "(ในเวลาทำการ)",
        "address": "เลขที่ 9/9 อาคารแอทสาทร ชั้น 20-27 ถนนสาทรใต้ แขวงยานนาวา เขตสาทร กรุงเทพฯ 10120",
        "email": "hotline@prudential.co.th",
        "working_hour": "เวลาทำการ:",
        "working_detail": "วันจันทร์ - วันศุกร์ เวลา 8.30-17.00 น. (ยกเว้น วันหยุดประจำปี)",
        "fax": "โทรสาร 0 2353 4888",
        "faq": "https://www.prudential.co.th/corp/prudential-th/th/our-services/faq/index.html",
        "img": {
            "logo": "logo",
            "email": "email-white",
            "complaint": "complaint-red",
            "address": "pin-red",
            "working_hour": "time-red",
            "fax": "telephone-red",
            "faq": "faq"
        }
    },
    "login": {
        "url": "/login",
        "liff_url": "https://liff.line.me/1557349447-kR8DxQnY",
        "user": {
            "id_card": 9906751334085,
            "line_id": "Ua22555c3da426d81d743f53a8bd0c184"
        },
        "img": {
            "logo": "media/logo",
            "otp": "OTP-SMS"
        }
    },
    "setting": {
        "url": "/setting?id=",
        "liff_url": "https://liff.line.me/1557349447-kR8DxQnY",
        "title": "การตั้งค่า",
        "user": {
            "id_card": 9906751334085,
            "line_id": "Ua22555c3da426d81d743f53a8bd0c184"
        },
        "img": {
            "logo": "pru-logo",
            "warning": "calculate-error",
            "logout": "confirm-logout"
        }
    },
    "payment": {
        "url": "/payment?id=",
        "title1": "กรุณาเลือกกรมธรรม์",
        "title2": "ที่ต้องการทำรายการ",
        "remark": "วิธีการชำระเบี้ยประกันภัย :",
        "user": {
            "id_card": 9906751334085,
            "line_id": "Ua22555c3da426d81d743f53a8bd0c184"
        },
        "img": {
            "logo": "pru-logo"
        }
    },
    "payment_method": {
        "title1": "สมัครบริการ",
        "title2": "หักค่าเบี้ยประกันภัยอัตโนมัติ",
        "atm_title": "กรุณาเลือกธนาคารเจ้าของบัญชี",
        "order_header": "รายละเอียดเพื่อใช้ในการทำรายการที่ตู้ ATM",
        "img": {
            "bank_account": "change-payment"
        },
        "comp": {
            "tmb": "บจก. พรูเด็นเชียล ประกันชีวิต",
            "tbank": "20078",
            "ktb": "6106",
            "kbank": "10647",
            "bay": "7771002357",
            "scb": "8074",
            "bbl": "65107"
        },
        "link": {
            "scb": "https://www.scbeasy.com/v1.4/site/presignon/index.asp",
            "bbl": "https://ibanking.bangkokbank.com/SignOn.aspx",
            "bay": "https://www.krungsrionline.com/BAY.KOL.WebSite/Common/Login.aspx"
        }
    },
    "payment_details": {
        "atm": [
            "ใส่บัตร ATM และกดรหัสบัตร",
            "เลือก “สมัครบริการ”",
            "เลือก “หักบัญชีอัตโนมัติ”",
            "เลือกบริษัทที่ต้องการหักบัญชีหรือระบุ Comp. Code",
            "ใส่หมายเลขอ้างอิง Reference No.",
            "ตรวจสอบข้อมูล และ กด “ยืนยัน” การทำรายการ"
        ],
        "mobile": [
            "เข้าสู่ระบบ",
            "เลือก “สมัครหักบัญชีอัตโนมัติ”",
            "เลือก “หักบัญชีอัตโนมัติ”",
            "เลือกบัญชีที่ต้องการสมัครใช้บริการ",
            "ค้นหาบริษัทผู้รับชำระ",
            "ใส่หมายเลขอ้างอิง Reference No.",
            "ตรวจสอบข้อมูล และ กด “ยืนยัน” การทำรายการ"
        ],
        "internet": [
            "Login เข้าใช้บริการ",
            "กดเลือก “สมัคร/ซื้อ บริการอื่นๆ”",
            "ค้นหาบริษัทผู้รับชำระ",
            "ใส่หมายเลขอ้างอิง Reference No.",
            "ยืนยันการทํารายการด้วย OTP ตรวจสอบข้อมูลของลูกค้า และกด “Submit”",
            "ระบบฯ แจ้งว่า ทํารายการสําเร็จ คลิก “Print” เพื่อพิมพ์หลักฐานการอนุมัติบริการหักบัญชีอัตโนมัติ"
        ]
    },
    "pru_details": {
        "super_link": {
            "atm": [
                "bbl",
                "scb"
            ],
            "mobile": [
                "scb"
            ],
            "internet": [
                "bbl",
                "scb"
            ]
        },
        "healthy": {
            "atm": [
                "tmb",
                "tbank",
                "ktb",
                "bbl",
                "kbank",
                "scb",
                "bay"
            ],
            "mobile": [
                "scb",
                "bay"
            ],
            "internet": [
                "bbl",
                "scb",
                "bay"
            ]
        },
        "smile_retirement": {
            "atm": [
                "tmb",
                "tbank",
                "ktb",
                "bbl",
                "kbank",
                "scb",
                "bay"
            ],
            "mobile": [
                "scb",
                "bay"
            ],
            "internet": [
                "bbl",
                "scb",
                "bay"
            ]
        },
        "whole_life": {
            "atm": [
                "tmb",
                "tbank",
                "ktb",
                "bbl",
                "kbank",
                "scb",
                "bay"
            ],
            "mobile": [
                "scb",
                "bay"
            ],
            "internet": [
                "bbl",
                "scb",
                "bay"
            ]
        },
        "happy_retirement": {
            "atm": [
                "tmb",
                "tbank",
                "ktb",
                "bbl",
                "kbank",
                "scb",
                "bay"
            ],
            "mobile": [
                "scb",
                "bay"
            ],
            "internet": [
                "bbl",
                "scb",
                "bay"
            ]
        },
        "endowment": {
            "atm": [
                "tmb",
                "tbank",
                "ktb",
                "bbl",
                "kbank",
                "scb",
                "bay"
            ],
            "mobile": [
                "scb",
                "bay"
            ],
            "internet": [
                "bbl",
                "scb",
                "bay"
            ]
        }
    }
}